sliced_wasserstein/__init__.py
sliced_wasserstein/gsw.py
sliced_wasserstein-0.1.0.dist-info/METADATA
sliced_wasserstein-0.1.0.dist-info/WHEEL
sliced_wasserstein-0.1.0.dist-info/top_level.txt
sliced_wasserstein-0.1.0.dist-info/RECORD
